onyxerp/__init__.py
onyxerp/core/__init__.py
onyxerp/core/api/__init__.py
onyxerp/core/api/request.py
onyxerp/core/api/response.py
onyxerp/core/services/__init__.py
onyxerp/core/services/account_service.py
onyxerp/core/services/app_service.py
onyxerp/core/services/auth_service.py
onyxerp/core/services/author_service.py
onyxerp/core/services/base_service.py
onyxerp/core/services/bio_service.py
onyxerp/core/services/cache_service.py
onyxerp/core/services/drive_service.py
onyxerp/core/services/file_service.py
onyxerp/core/services/generator.py
onyxerp/core/services/gov_service.py
onyxerp/core/services/governanca_service.py
onyxerp/core/services/jwt_service.py
onyxerp/core/services/login_service.py
onyxerp/core/services/meta_service.py
onyxerp/core/services/onyxerp_service.py
onyxerp/core/services/s3_service.py
onyxerp/core/services/simulador_service.py
onyxerp/core/services/sms_service.py
onyxerp/core/services/social_service.py
onyxerp/core/services/social_service_v2.py
onyxerp/core/services/thread_service.py
onyxerp/core/services/ufcidade_service.py
onyxerp/core/services/versao_registro_service.py
onyxerp/core/validators/__init__.py
onyxerp/core/validators/erp_validators.py
onyxerp-2.1.0.dist-info/METADATA
onyxerp-2.1.0.dist-info/RECORD
onyxerp-2.1.0.dist-info/WHEEL
onyxerp-2.1.0.dist-info/top_level.txt
