Metadata-Version: 2.1
Name: onyxerp
Version: 2.1.0
Summary: Utilities do OnyxERP
Home-page: https://github.com/BRAConsultoria/OnyexERPy
Author: Rinzler
Author-email: feliphezion@gmail.com
License: MIT
Keywords: rest,api,framework,django
Platform: UNKNOWN
Classifier: Development Status :: 3 - Alpha
Classifier: Intended Audience :: Developers
Classifier: Topic :: Software Development
Classifier: License :: OSI Approved :: MIT License
Classifier: Programming Language :: Python :: 2
Classifier: Programming Language :: Python :: 2.7
Classifier: Programming Language :: Python :: 3
Classifier: Programming Language :: Python :: 3.3
Classifier: Programming Language :: Python :: 3.4
Classifier: Programming Language :: Python :: 3.5
Requires-Dist: requests
Requires-Dist: rinzler
Requires-Dist: pyjwt
Requires-Dist: boto3
Requires-Dist: botocore
Provides-Extra: dev
Requires-Dist: check-manifest; extra == 'dev'
Provides-Extra: test
Requires-Dist: coverage; extra == 'test'
